flashnn/__init__.py
flashnn/attention.py
flashnn/kernel_backend.py
flashnn/logits_processor.py
flashnn/norm.py
flashnn/quant_gemm.py
flashnn/rotary_embedding.py
flashnn/triton_kernels/__init__.py
flashnn/triton_kernels/dynamic_quant.py
flashnn/triton_kernels/flash_attn_v2.py
flashnn/triton_kernels/fused_moe_a16w4.py
flashnn/triton_kernels/fused_moe_a8w8.py
flashnn/triton_kernels/fused_moe_fp16.py
flashnn/triton_kernels/gemm_a16w4.py
flashnn/triton_kernels/gemm_a16w8.py
flashnn/triton_kernels/gemm_a8w8.py
flashnn/triton_kernels/layer_norm.py
flashnn/triton_kernels/layer_norm_dquant.py
flashnn/triton_kernels/logits_processor.py
flashnn/triton_kernels/paged_attn.py
flashnn/triton_kernels/paged_attn_v1.py
flashnn/triton_kernels/paged_attn_v2.py
flashnn/triton_kernels/rms_norm.py
flashnn/triton_kernels/rms_norm_dquant.py
flashnn/triton_kernels/rotary_embedding.py
flashnn/triton_kernels/triton_utils.py
tests/__init__.py
tests/run_tests.py
tests/test_logits_processor.py
tests/test_rotary_embedding.py
flashnn-0.1.1.dist-info/LICENSE
flashnn-0.1.1.dist-info/METADATA
flashnn-0.1.1.dist-info/WHEEL
flashnn-0.1.1.dist-info/top_level.txt
flashnn-0.1.1.dist-info/RECORD
