Metadata-Version: 2.1
Name: flashnn
Version: 0.1.1
Summary: Flash: Triton Kernel Library for LLM Serving
Home-page: https://github.com/AlibabaPAI/FLASHNN
Author: Alibaba PAI Team
Classifier: Intended Audience :: Developers
Classifier: Topic :: Scientific/Engineering :: Artificial Intelligence
Classifier: Topic :: Software Development :: Libraries :: Python Modules
License-File: LICENSE
Requires-Dist: torch
Requires-Dist: triton
